{
    "C": [
        0.0,
        1.5,
        33.5,
        35.0,
        36.5,
        38.0,
        70.0,
        71.5,
        73.0,
        74.5,
        76.0,
        77.5,
        79.0,
        80.5,
        82.0,
        83.5,
        85.0,
        86.5,
        88.0,
        89.5,
        91.0,
        92.5,
        94.0,
        95.5,
        127.5,
        159.5,
        191.5,
        223.5,
        255.5,
        287.5,
        289.0,
        290.5,
        292.0,
        293.5,
        295.0,
        296.5,
        298.0,
        299.5,
        301.0
    ],
    "actions": [
        0,
        1,
        0,
        0,
        0,
        1,
        0,
        0,
        0,
        0,
        0,
        0,
        0,
        0,
        0,
        0,
        0,
        0,
        0,
        0,
        0,
        0,
        0,
        1,
        1,
        1,
        1,
        1,
        1,
        0,
        0,
        0,
        0,
        0,
        0,
        0,
        0,
        0
    ],
    "best_intervention_levels": {
        "0": [
            [
                0.0,
                0.0
            ],
            [
                0.0,
                0.0
            ],
            [
                0.0,
                0.0
            ],
            [
                0.0,
                0.0
            ],
            [
                0.0,
                0.0
            ],
            [
                1.0,
                0.0
            ],
            [
                1.0,
                0.0
            ],
            [
                0.0,
                1.0
            ],
            [
                0.0,
                1.0
            ],
            [
                0.0,
                1.0
            ],
            [
                0.0,
                1.0
            ],
            [
                0.0,
                1.0
            ],
            [
                0.0,
                1.0
            ],
            [
                0.0,
                1.0
            ],
            [
                0.0,
                1.0
            ],
            [
                0.0,
                1.0
            ],
            [
                0.0,
                1.0
            ],
            [
                0.0,
                1.0
            ],
            [
                0.0,
                1.0
            ],
            [
                0.0,
                1.0
            ],
            [
                0.0,
                1.0
            ],
            [
                0.0,
                1.0
            ],
            [
                0.0,
                1.0
            ],
            [
                0.0,
                1.0
            ],
            [
                0.0,
                1.0
            ],
            [
                0.0,
                1.0
            ],
            [
                0.0,
                1.0
            ],
            [
                0.0,
                1.0
            ],
            [
                0.0,
                1.0
            ],
            [
                0.0,
                1.0
            ],
            [
                0.0,
                1.0
            ],
            [
                0.0,
                1.0
            ],
            [
                0.0,
                1.0
            ],
            [
                0.0,
                1.0
            ],
            [
                0.0,
                1.0
            ],
            [
                0.0,
                1.0
            ],
            [
                0.0,
                1.0
            ],
            [
                0.0,
                1.0
            ],
            [
                0.0,
                1.0
            ]
        ]
    },
    "best_intervention_set": [
        [
            "C",
            "D"
        ],
        [
            "C",
            "D"
        ],
        [
            "C",
            "D"
        ],
        [
            "C",
            "D"
        ],
        [
            "C",
            "D"
        ],
        [
            "C",
            "D"
        ],
        [
            "C",
            "D"
        ],
        [
            "C",
            "D"
        ],
        [
            "C",
            "D"
        ],
        [
            "C",
            "D"
        ],
        [
            "C",
            "D"
        ],
        [
            "C",
            "D"
        ],
        [
            "C",
            "D"
        ],
        [
            "C",
            "D"
        ],
        [
            "C",
            "D"
        ],
        [
            "C",
            "D"
        ],
        [
            "C",
            "D"
        ],
        [
            "C",
            "D"
        ],
        [
            "C",
            "D"
        ],
        [
            "C",
            "D"
        ],
        [
            "C",
            "D"
        ],
        [
            "C",
            "D"
        ],
        [
            "C",
            "D"
        ],
        [
            "C",
            "D"
        ],
        [
            "C",
            "D"
        ],
        [
            "C",
            "D"
        ],
        [
            "C",
            "D"
        ],
        [
            "C",
            "D"
        ],
        [
            "C",
            "D"
        ],
        [
            "C",
            "D"
        ],
        [
            "C",
            "D"
        ],
        [
            "C",
            "D"
        ],
        [
            "C",
            "D"
        ],
        [
            "C",
            "D"
        ],
        [
            "C",
            "D"
        ],
        [
            "C",
            "D"
        ],
        [
            "C",
            "D"
        ],
        [
            "C",
            "D"
        ],
        [
            "C",
            "D"
        ]
    ],
    "best_intervention_targets": {
        "0": [
            Infinity,
            Infinity,
            Infinity,
            5.518699323875259,
            5.518699323875259,
            5.518699323875259,
            5.346725808265351,
            5.159083476574843,
            5.159083476574843,
            5.157967602761971,
            5.157967602761971,
            5.155735968781125,
            5.1538521311023535,
            5.153712576564544,
            5.153712576564544,
            5.153712576564544,
            5.153712576564544,
            5.1530410844408685,
            5.1530410844408685,
            5.1530410844408685,
            5.1530410844408685,
            5.1530410844408685,
            5.150815890814971,
            5.150815890814971,
            5.150815890814971,
            5.150815890814971,
            5.150815890814971,
            5.15034107241728,
            5.15034107241728,
            5.15034107241728,
            5.15034107241728,
            5.15034107241728,
            5.15034107241728,
            5.15034107241728,
            5.15034107241728,
            5.15034107241728,
            5.15034107241728,
            5.15034107241728,
            5.15034107241728
        ]
    },
    "cumulative_cost": 301.0,
    "evaluation_budget": 300,
    "exp_bonuses": [
        Infinity,
        5.212623192389065,
        4.235929801913757,
        4.203350091046294,
        6.98680483198456,
        4.707316794607203,
        5.201771592246073,
        4.498261045207382,
        3.9577843277133815,
        3.3746059060195144,
        3.9682341451457135,
        2.6091096927986372,
        2.2674801800867344,
        2.9860796617493497,
        4.169478407696427,
        2.332014565684635,
        1.910971574586283,
        3.369302618119227,
        2.5965681485089647,
        1.9588545479708999,
        2.6571815663882377,
        1.2356465499976517,
        1.3086596185690325,
        1.3332173869291375,
        1.2044294677927636,
        1.2889640343088966,
        1.2947848765718142
    ],
    "exploration_set": [
        [
            "C",
            "D"
        ]
    ],
    "information_gains": [
        0.012197241019741723,
        0.031796049122289075,
        -2.3307435329811588,
        -3.1541303110191112,
        4.422764873381642e-06,
        1.1679226235541701e-06,
        -9.87740513156239e-07,
        -2.6283086089843525e-05,
        0.5087824854894536,
        -1.0499323623681437e-09,
        -2.335888814872529e-10,
        0.002628989697739453,
        0.008911348206401623,
        0.056249501431866314,
        0.0022271642642501064,
        -2.895571781109747e-10,
        -1.3199950016318816e-10,
        -1.730182885161731e-10,
        0.00020778207005602345,
        0.14807702164560402,
        -3.8088454592555205e-10,
        -2.99025670742868e-10,
        -8.306688670237796e-14,
        -6.3504757008544616e-15,
        1.4025302550947863e-07,
        1.2952573762801663e-05,
        2.9351380261192366e-06,
        0,
        0,
        0,
        0,
        0,
        0,
        0,
        0,
        0
    ],
    "intervention_data": [
        [
            [
                "C",
                "D"
            ],
            [
                [
                    0.284771026179954,
                    0.6663794231276026
                ],
                [
                    0.1369496701610782,
                    0.8073287248363127
                ],
                [
                    0.13696369088690247,
                    0.8073226231660711
                ],
                [
                    0.13694514555637752,
                    0.8073309606387834
                ],
                [
                    0.13694992634824868,
                    0.8073288965796187
                ],
                [
                    0.13829616536170558,
                    0.8007204859009952
                ],
                [
                    0.15793308204161596,
                    0.6836354325434274
                ],
                [
                    0.0625166531786199,
                    0.8532573486834327
                ]
            ],
            [
                [
                    5.518699323875259
                ],
                [
                    5.346725808265351
                ],
                [
                    5.347954747318737
                ],
                [
                    5.347518248416062
                ],
                [
                    5.348568700972339
                ],
                [
                    5.352470376136707
                ],
                [
                    5.4354189565476965
                ],
                [
                    5.279555575163087
                ]
            ]
        ]
    ],
    "interventions": [
        [
            "C",
            "D"
        ],
        [
            "C",
            "D"
        ],
        [
            "C",
            "D"
        ],
        [
            "C",
            "D"
        ],
        [
            "C",
            "D"
        ],
        [
            "C",
            "D"
        ],
        [
            "C",
            "D"
        ],
        [
            "C",
            "D"
        ]
    ],
    "iteration": 36,
    "mean_gains": [
        -0.01973950093786314,
        -0.012518551172313153,
        0.1260456179223466,
        0.2337030961633646,
        0.004243140525246325,
        0.0033690087637348043,
        0.0011671673367530389,
        0.023439642649727865,
        0.03844726730273784,
        -6.099912261881002e-05,
        -2.994202082184927e-05,
        0.05627602408720467,
        0.06161158013320289,
        -0.6222409343854887,
        0.0036097529313083854,
        -5.590235468666549e-05,
        -3.3043141248967345e-05,
        -4.02561529515566e-05,
        -0.017827618568669656,
        0.13681193202958664,
        -6.127798564126152e-05,
        -5.2178870415531264e-05,
        -1.463650318367371e-05,
        -8.925998020714587e-07,
        -0.004918967554696785,
        -0.009998145338749431,
        0.01911400435979882,
        0,
        0,
        0,
        0,
        0,
        0,
        0,
        0,
        0
    ],
    "num_intervene_decisions": 8,
    "num_observe_decisions": 30,
    "observation_data": {
        "A,B,C,D,E,F": [
            [
                68.84966999688304,
                25.66090447610028,
                0.4145454668165519,
                0.27232623038005144,
                0.2712130836606631,
                -6.095666187587549
            ],
            [
                58.050054290807935,
                24.99520669824591,
                0.19075090344574114,
                0.10011447934768523,
                0.38870945475771684,
                -5.539587879928772
            ],
            [
                57.47966839508938,
                27.060921640213618,
                0.1915135259792435,
                0.13706917187603454,
                0.40010522262745307,
                -5.7005452178533815
            ],
            [
                65.91867644262501,
                26.131301260519585,
                0.3488283485019286,
                0.23471575399761616,
                0.30216006304796544,
                -5.8629307262476305
            ],
            [
                57.063049089755076,
                27.209943523116774,
                0.18582094152065987,
                0.13567267215918327,
                0.4054605459930226,
                -5.686145658218199
            ],
            [
                61.4695590254189,
                25.89451021195434,
                0.2542241379813942,
                0.157872716395132,
                0.35074564057258056,
                -5.732862498961453
            ],
            [
                66.77525605767384,
                25.530947584672642,
                0.36434703243062133,
                0.2285909038962321,
                0.292078621485123,
                -5.621799859250089
            ],
            [
                70.59492219091509,
                25.730711208826786,
                0.4579529280480712,
                0.31123207299237055,
                0.2543150722646667,
                -5.764542629093225
            ],
            [
                74.26589474858858,
                25.378318949521244,
                0.5468469515160519,
                0.3780703403119511,
                0.22033805822422733,
                -6.556346471623167
            ],
            [
                68.35754728186551,
                25.724956584699957,
                0.40311644601651875,
                0.26517274655263895,
                0.27624348150962913,
                -6.4268247458015955
            ],
            [
                56.4327747921301,
                26.507263757056077,
                0.17343085156029872,
                0.11352098242540319,
                0.4115313810093738,
                -5.685866891095468
            ],
            [
                65.31180142315262,
                26.78255475684289,
                0.33954035579586533,
                0.247440687681447,
                0.3098391608061681,
                -6.876491586273602
            ],
            [
                61.69548848784716,
                27.059049349748964,
                0.2652846644474777,
                0.19487467619630233,
                0.3505384521478555,
                -5.749225971128693
            ],
            [
                55.79025068905422,
                26.65348935718893,
                0.16501598259978878,
                0.11004543747162628,
                0.41968195342945697,
                -5.364928105857933
            ],
            [
                68.35829178880357,
                26.84241254411674,
                0.41122624752349785,
                0.31094858534410713,
                0.27814055169062357,
                -5.372754878352393
            ],
            [
                61.74637845640052,
                25.484243281462494,
                0.2571499449748814,
                0.15077781841128687,
                0.3467480160450261,
                -5.767989710962949
            ],
            [
                64.36015701695037,
                26.141808430171626,
                0.3143780703749216,
                0.20823084006609985,
                0.3189434693901502,
                -5.5814416969802645
            ],
            [
                70.18010100551004,
                26.37707904271404,
                0.4524745247295523,
                0.33035628230373026,
                0.2593405220475288,
                -6.877150562691268
            ],
            [
                61.39300093993921,
                26.047702731076328,
                0.25364440985477044,
                0.16095232034643642,
                0.35193643145783177,
                -5.375883110893633
            ],
            [
                72.06701913880906,
                26.05388766374057,
                0.49707966915636276,
                0.3583528208231932,
                0.24100004466006583,
                -5.542515814751766
            ],
            [
                63.20668626888782,
                26.08886912387123,
                0.2897362611415905,
                0.18822921784123386,
                0.3315506440231689,
                -5.6912778734014715
            ],
            [
                62.31817113970993,
                25.413924292820045,
                0.2678094337024199,
                0.15638200343863598,
                0.34014044624628254,
                -5.046836696309445
            ],
            [
                72.5255150000764,
                26.09220199617961,
                0.5088284723241081,
                0.37074826248091364,
                0.23685370252682206,
                -5.818706364148424
            ],
            [
                55.42478220513876,
                25.595280693385593,
                0.15582011686186695,
                0.08798696206460675,
                0.4217266368174751,
                -5.463317825944885
            ],
            [
                61.65299322500238,
                26.230220100755606,
                0.2596489240002965,
                0.16957297978051325,
                0.3493409481656084,
                -5.9385658772988
            ],
            [
                62.99237930321924,
                26.807622229365656,
                0.28976340478444784,
                0.20763545900264296,
                0.33535733996171735,
                -5.91144431241389
            ],
            [
                59.05261070387653,
                26.64836860417191,
                0.21495912858244878,
                0.14615709246733466,
                0.3804369643043568,
                -5.303618382990073
            ],
            [
                74.13277392091597,
                24.445724140861014,
                0.5365967152746103,
                0.33234948385515506,
                0.22015840603915576,
                -6.10035671246612
            ],
            [
                66.85694023734679,
                27.347848151299143,
                0.37898219410721373,
                0.3005381934439358,
                0.29446205310882156,
                -5.191472303875057
            ],
            [
                74.19283640459852,
                26.656569530148595,
                0.5545274612625324,
                0.437970581131519,
                0.22278594152988887,
                -5.630836133662132
            ]
        ]
    },
    "observation_gains": [
        Infinity,
        3.7569377926836722,
        0.2791406510102519,
        -0.6844833161361805,
        5.482566114224181,
        3.203948953766087,
        3.700603437168809,
        2.9747951194715654,
        2.9281195459001026,
        1.8746669040921944,
        2.4682640869329475,
        1.0554626584091764,
        0.7147799481599364,
        2.1645700975667097,
        2.668095819029368,
        0.8320704677497659,
        0.4110046175955375,
        1.8693428740991536,
        1.114603549147688,
        0.47011963758691877,
        1.1572428439929894,
        -0.26430127143095206,
        -0.19132574492786603,
        -0.16678172047107154,
        -0.2906514243995062,
        -0.2010248677785853,
        -0.22432619264996134,
        0,
        0,
        0,
        0,
        0,
        0,
        0,
        0,
        0
    ],
    "optimal_intervention_mean": 5.15447651807516,
    "remaining_budget": -1.0,
    "start_time": 1681803209.2088625,
    "total_time": 1609.319094657898
}